blobular/__about__.py
blobular/__init__.py
blobular/registry.py
blobular/util.py
blobular/api/api.py
blobular/api/app.py
blobular/api/authentication.py
blobular/api/github_login.py
blobular/api/persist.py
blobular/api/settings.py
blobular/api/web.py
blobular/cli/__main__.py
blobular/cli/cli.py
blobular/cli/cloudutils.py
blobular/cli/console.py
blobular/cli/filesnap.py
blobular/cli/login.py
blobular/cli/settings.py
blobular/cli/state.py
blobular/store/__init__.py
blobular/store/abstract.py
blobular/store/cache.py
blobular/store/cloud.py
blobular/store/db.py
blobular/store/localfile.py
blobular/store/mem.py
blobular/store/s3.py
blobular-0.0.5.dist-info/METADATA
blobular-0.0.5.dist-info/WHEEL
blobular-0.0.5.dist-info/entry_points.txt
blobular-0.0.5.dist-info/licenses/LICENSE.txt
blobular-0.0.5.dist-info/RECORD
